adversarial_examples/__init__.py
adversarial_examples/adversarial.py
adversarial_examples/utils.py
adversarial_examples-0.1.1.dist-info/LICENSE
adversarial_examples-0.1.1.dist-info/METADATA
adversarial_examples-0.1.1.dist-info/WHEEL
adversarial_examples-0.1.1.dist-info/RECORD
